supadantic/__init__.py
supadantic/clients/__init__.py
supadantic/clients/base.py
supadantic/clients/cache.py
supadantic/clients/supabase.py
supadantic/models.py
supadantic/q_set.py
supadantic/query_builder.py
supadantic/utils.py
supadantic-0.0.11.dist-info/LICENSE
supadantic-0.0.11.dist-info/METADATA
supadantic-0.0.11.dist-info/WHEEL
supadantic-0.0.11.dist-info/RECORD
