Metadata-Version: 2.3
Name: supadantic
Version: 0.0.11
Summary: Supabase integration for pydantic
License: MIT
Author: Alexey Makridenko
Author-email: alexey.makridenko@gmail.com
Requires-Python: >=3.10,<4.0
Classifier: License :: OSI Approved :: MIT License
Classifier: Programming Language :: Python :: 3
Classifier: Programming Language :: Python :: 3.10
Classifier: Programming Language :: Python :: 3.11
Classifier: Programming Language :: Python :: 3.12
Classifier: Programming Language :: Python :: 3.13
Requires-Dist: pydantic (>=2.11.0,<3.0.0)
Requires-Dist: supabase (>=2.4.2,<3.0.0)
